{
  "schemaVersion": "1.0.0",
  "readme": "",
  "modules": [
    {
      "kind": "javascript-module",
      "path": "src/furo-config-loader.js",
      "declarations": [
        {
          "kind": "class",
          "description": "`furo-config-loader`\n\nladet eine Konfiguration in eine vorgegebene Sektion. Diese lassen sich mit furo-config in jeder Komponente verwenden.\n\n```\n  <furo-config-loader src=\"/custom/view-config.json\" section=\"views\"></furo-config-loader>\n\n```",
          "name": "FuroConfigLoader",
          "members": [
            {
              "kind": "method",
              "name": "_FBPReady",
              "description": "flow is ready lifecycle method",
              "privacy": "private"
            },
            {
              "kind": "field",
              "name": "src",
              "privacy": "public",
              "description": "src\nQuelle der Konfiguration",
              "attribute": "src"
            },
            {
              "kind": "field",
              "name": "section",
              "privacy": "public",
              "description": "section\nDie Sektion in der die Antwort gesichert wird",
              "attribute": "section"
            }
          ],
          "events": [
            {
              "type": {
                "text": "Object"
              },
              "description": "Fired when the config is loaded with the loaded config as detail.",
              "name": "config-loaded"
            }
          ],
          "attributes": [
            {
              "name": "src",
              "description": "src\nQuelle der Konfiguration",
              "fieldName": "src"
            },
            {
              "name": "section",
              "description": "section\nDie Sektion in der die Antwort gesichert wird",
              "fieldName": "section"
            }
          ],
          "mixins": [
            {
              "name": "FBP",
              "package": "@furo/fbp"
            }
          ],
          "superclass": {
            "name": "LitElement",
            "package": "lit-element"
          },
          "summary": "load config files",
          "tagName": "furo-config-loader",
          "customElement": true
        }
      ],
      "exports": [
        {
          "kind": "custom-element-definition",
          "name": "furo-config-loader",
          "declaration": {
            "name": "FuroConfigLoader",
            "module": "src/furo-config-loader.js"
          }
        }
      ]
    },
    {
      "kind": "javascript-module",
      "path": "src/furo-config.js",
      "declarations": [
        {
          "kind": "class",
          "description": "`furo-config`\n\n Access config data\n\n\n```html\n  <furo-config-loader section=\"views\" src=\"/viewconfig.json\"></furo-config>\n  <furo-config-loader section=\"second\" src=\"/second.json\"></furo-config>\n  <furo-config section=\"views\" @-config-updated=\"--conf\"></furo-config>\n  <furo-config section=\"second.section.deep\" @-config-updated=\"--deepconf\"></furo-config>\n```",
          "name": "FuroConfig",
          "members": [
            {
              "kind": "field",
              "name": "section",
              "privacy": "public",
              "description": "section of the config object that you are interested in\n\naccess deep object with dots like `main.sub.sub`",
              "attribute": "section"
            },
            {
              "kind": "field",
              "name": "config",
              "description": "The current section of the config, which was defined by `section`.",
              "default": "Config"
            }
          ],
          "events": [
            {
              "type": {
                "text": "config.section"
              },
              "description": "Fired when section changed",
              "name": "config-updated"
            }
          ],
          "attributes": [
            {
              "name": "section",
              "description": "section of the config object that you are interested in\n\naccess deep object with dots like `main.sub.sub`",
              "fieldName": "section"
            }
          ],
          "superclass": {
            "name": "LitElement",
            "package": "lit-element"
          },
          "summary": "config access",
          "tagName": "furo-config",
          "customElement": true
        }
      ],
      "exports": [
        {
          "kind": "custom-element-definition",
          "name": "furo-config",
          "declaration": {
            "name": "FuroConfig",
            "module": "src/furo-config.js"
          }
        }
      ]
    },
    {
      "kind": "javascript-module",
      "path": "src/lib/Config.js",
      "declarations": [
        {
          "kind": "class",
          "description": "",
          "name": "Config",
          "members": [
            {
              "kind": "method",
              "name": "append",
              "static": true,
              "parameters": [
                {
                  "name": "section"
                },
                {
                  "name": "obj"
                }
              ]
            },
            {
              "kind": "method",
              "name": "deepCreate",
              "static": true,
              "parameters": [
                {
                  "name": "parent"
                },
                {
                  "name": "section"
                },
                {
                  "name": "obj"
                }
              ],
              "description": "create nodes a long they are objects"
            },
            {
              "kind": "method",
              "name": "watch",
              "static": true,
              "parameters": [
                {
                  "name": "section"
                },
                {
                  "name": "cb"
                }
              ]
            }
          ]
        }
      ],
      "exports": [
        {
          "kind": "js",
          "name": "Config",
          "declaration": {
            "name": "Config",
            "module": "src/lib/Config.js"
          }
        }
      ]
    }
  ]
}
